OctoBot_Backtesting-1.8.2.dist-info/LICENSE
OctoBot_Backtesting-1.8.2.dist-info/WHEEL
OctoBot_Backtesting-1.8.2.dist-info/top_level.txt
OctoBot_Backtesting-1.8.2.dist-info/RECORD
OctoBot_Backtesting-1.8.2.dist-info/METADATA
octobot_backtesting/backtest_data.py
octobot_backtesting/channels_manager.cpython-38-i386-linux-gnu.so
octobot_backtesting/constants.py
octobot_backtesting/channels_manager.pxd
octobot_backtesting/__init__.pxd
octobot_backtesting/enums.py
octobot_backtesting/backtesting.py
octobot_backtesting/backtest_data.pxd
octobot_backtesting/channels_manager.py
octobot_backtesting/__init__.py
octobot_backtesting/errors.py
octobot_backtesting/backtesting.pxd
octobot_backtesting/backtest_data.cpython-38-i386-linux-gnu.so
octobot_backtesting/backtesting.cpython-38-i386-linux-gnu.so
octobot_backtesting/importers/data_importer.pxd
octobot_backtesting/importers/__init__.pxd
octobot_backtesting/importers/data_importer.py
octobot_backtesting/importers/__init__.py
octobot_backtesting/importers/data_importer.cpython-38-i386-linux-gnu.so
octobot_backtesting/importers/social/social_importer.pxd
octobot_backtesting/importers/social/__init__.pxd
octobot_backtesting/importers/social/__init__.py
octobot_backtesting/importers/social/social_importer.py
octobot_backtesting/importers/social/social_importer.cpython-38-i386-linux-gnu.so
octobot_backtesting/importers/exchanges/exchange_importer.cpython-38-i386-linux-gnu.so
octobot_backtesting/importers/exchanges/__init__.pxd
octobot_backtesting/importers/exchanges/exchange_importer.py
octobot_backtesting/importers/exchanges/util.pxd
octobot_backtesting/importers/exchanges/__init__.py
octobot_backtesting/importers/exchanges/util.py
octobot_backtesting/importers/exchanges/exchange_importer.pxd
octobot_backtesting/importers/exchanges/util.cpython-38-i386-linux-gnu.so
octobot_backtesting/converters/__init__.pxd
octobot_backtesting/converters/__init__.py
octobot_backtesting/converters/data_converter.py
octobot_backtesting/converters/data_converter.pxd
octobot_backtesting/converters/data_converter.cpython-38-i386-linux-gnu.so
octobot_backtesting/api/backtesting.py
octobot_backtesting/api/__init__.py
