Metadata-Version: 2.1
Name: OctoBot-Backtesting
Version: 1.8.2
Summary: OctoBot project backtesting engine
Home-page: https://github.com/Drakkar-Software/OctoBot-Backtesting
Author: Drakkar-Software
Author-email: drakkar-software@protonmail.com
License: LGPL-3.0
Platform: UNKNOWN
Classifier: Development Status :: 5 - Production/Stable
Classifier: Operating System :: OS Independent
Classifier: Operating System :: MacOS :: MacOS X
Classifier: Operating System :: Microsoft :: Windows
Classifier: Operating System :: POSIX
Classifier: Programming Language :: Python :: 3.8
Classifier: Programming Language :: Python :: 3.9
Classifier: Programming Language :: Cython
Requires-Python: >=3.8
Requires-Dist: cython (==0.29.32)
Requires-Dist: Async-Channel (<2.2,>=2.1)
Requires-Dist: OctoBot-Commons (<1.9,>=1.8)
Requires-Dist: OctoBot-Tentacles-Manager (<2.9,>=2.8)
Requires-Dist: aiohttp (>=3.8.1)
